pyrmq/__init__.py
pyrmq/consumer.py
pyrmq/publisher.py
pyrmq/tests/__init__.py
pyrmq/tests/conftest.py
pyrmq/tests/test_consumer.py
pyrmq/tests/test_publisher.py
pyrmq-4.0.0.dist-info/METADATA
pyrmq-4.0.0.dist-info/WHEEL
pyrmq-4.0.0.dist-info/licenses/AUTHORS
pyrmq-4.0.0.dist-info/licenses/LICENSE
pyrmq-4.0.0.dist-info/RECORD
