Metadata-Version: 2.4
Name: PyRMQ
Version: 4.0.0
Summary: Python with RabbitMQ—simplified so you won't have to.
Project-URL: Documentation, https://pyrmq.readthedocs.io
Project-URL: Code, https://github.com/first-digital-finance/pyrmq
Project-URL: Issue tracker, https://github.com/first-digital-finance/pyrmq/issues
Author-email: Alexandre Gerona <alecgerona@gmail.com>
Maintainer-email: Jasper Sibayan <sibayanjasper@gmail.com>
License: MIT
License-File: AUTHORS
License-File: LICENSE
Keywords: consumer,messages,pika,publisher,queue,rabbitmq
Classifier: Development Status :: 5 - Production/Stable
Classifier: Intended Audience :: Developers
Classifier: License :: OSI Approved :: MIT License
Classifier: Natural Language :: English
Classifier: Operating System :: OS Independent
Classifier: Programming Language :: Python
Classifier: Programming Language :: Python :: 3
Classifier: Programming Language :: Python :: 3.11
Classifier: Programming Language :: Python :: 3.12
Classifier: Programming Language :: Python :: 3.13
Requires-Python: >=3.11
Requires-Dist: pika>=1.1.0
Provides-Extra: dev
Requires-Dist: pre-commit>=3.6.0; extra == 'dev'
Requires-Dist: pytest-cov>=4.1.0; extra == 'dev'
Requires-Dist: pytest>=8.0.0; extra == 'dev'
Provides-Extra: docs
Requires-Dist: pyyaml>=6.0.1; extra == 'docs'
Requires-Dist: sphinx>=8.2.3; extra == 'docs'
Provides-Extra: test
Requires-Dist: pytest-cov>=4.1.0; extra == 'test'
Requires-Dist: pytest>=8.0.0; extra == 'test'
